{
  "nodes": [
    {
      "id": "abad_musa",
      "name_arb": "عباد بْن مُوسَى الختلي",
      "val": "10"
    },
    {
      "id": "abdaziz_hatab",
      "name_arb": "عبد العزيز بْن الخطاب الكوفي",
      "val": "10"
    },
    {
      "id": "abdkebir_abdmexhid",
      "name_arb": "عبد الكبير بْن عَبد المجيد الحنفي",
      "val": "10"
    },
    {
      "id": "abdmelik_amr",
      "name_arb": "عبد المَلِك بْن عَمْرو العقدي",
      "val": "10"
    },
    {
      "id": "abdmelik_ibrahim",
      "name_arb": "عبد الملك بْن إِبْرَاهِيم الجدي",
      "val": "10"
    },
    {
      "id": "abdmelik_seid",
      "name_arb": "عبد الملك بْن سَعِيد بْن مروان الحراني",
      "val": "10"
    },
    {
      "id": "abdmelik_shuajb",
      "name_arb": "عبد الملك بْن شعيب بْن الليث بْن سعد المِصْرِي",
      "val": "10"
    },
    {
      "id": "abdrrahim_abdrrahman",
      "name_arb": "عبد الرحيم بْن عَبْد الرَّحْمَنِ بْن مُحَمَّد المحاربي",
      "val": "10"
    },
    {
      "id": "abdrrahman_ibrahim_dimeshk",
      "name_arb": "عبد الرحمن بْن إِبْرَاهِيم الدمشقي",
      "val": "10"
    },
    {
      "id": "abdrrahman_jahja_mahzum",
      "name_arb": "عبد الرحمن بْن يحيى بْن إِسْمَاعِيل المخزومي",
      "val": "10"
    },
    {
      "id": "abdrrahman_mehdi",
      "name_arb": "عبد الرحمن بْن مهدي",
      "val": "10"
    },
    {
      "id": "abdrrahman_vakid",
      "name_arb": "عَبْد الرَّحْمَنِ بْن واقد الواقدي ",
      "val": "10"
    },
    {
      "id": "abdrrezak_hemam",
      "name_arb": "عبد الرزاق بن همام الصعناني ",
      "val": "10"
    },
    {
      "id": "abdsamed_abdvarith",
      "name_arb": "عبد الصمد بْن عبد الوارث بْن سَعِيد التنوري ",
      "val": "10"
    },
    {
      "id": "abdselam_abdrrahman",
      "name_arb": "عبد السلام بْن عَبْد الرَّحْمَنِ بْن صخر الوابصي القاضي ",
      "val": "10"
    },
    {
      "id": "abdullah_ahmed_mukri",
      "name_arb": "عبد الله بْن أَحْمَد بْن بشير الدمشقي الْمُقْرِئ",
      "val": "10"
    },
    {
      "id": "abdullah_mejmun_kadah",
      "name_arb": "عبد الله بْن ميمون القداح",
      "val": "10"
    },
    {
      "id": "abdullah_mesleme_kanebi",
      "name_arb": "عبد الله بْن مسلمة بْن قعنب القعنبي",
      "val": "10"
    },
    {
      "id": "abdullah_mubarek",
      "name_arb": "عبد الله بْن المبارك",
      "val": "10"
    },
    {
      "id": "abdullah_muhamed_harrani",
      "name_arb": "عبد الله بن محمد ابن علي النفيلي الحراني",
      "val": "10"
    },
    {
      "id": "abdullah_muhamed_kermani",
      "name_arb": "عبد الله بْن مُحَمَّد بْن الربيع الكرماني",
      "val": "10"
    },
    {
      "id": "abdullah_numejr",
      "name_arb": "عبد الله بْن نمير الهمداني",
      "val": "10"
    },
    {
      "id": "abdullah_rebia",
      "name_arb": "عبد الله بْن ربيعة المصيصي",
      "val": "10"
    },
    {
      "id": "abdullah_salih_ixhli",
      "name_arb": "عبد الله بْن صَالِح العجلي",
      "val": "10"
    },
    {
      "id": "abdullah_salih_misri",
      "name_arb": "عَبد اللَّهِ بْن صَالِح المِصْرِي ",
      "val": "10"
    },
    {
      "id": "abdullah_xhafer_medini",
      "name_arb": "عبد الله بْن جَعْفَر بْن نجيح المديني",
      "val": "10"
    },
    {
      "id": "abdullah_xhafer_reki",
      "name_arb": "عبد الله بْن جَعْفَر الرَّقِّيّ ",
      "val": "10"
    },
    {
      "id": "abdullah_zubejr_humejd",
      "name_arb": "عبد الله بْن الزبير الحميدي ",
      "val": "10"
    },
    {
      "id": "abdvehab_nexhde",
      "name_arb": "عبد الوهاب بْن نجدة الحوطي",
      "val": "10"
    },
    {
      "id": "abther_kasim",
      "name_arb": "عبثر بْن الْقَاسِم الزبيدي الكوفي",
      "val": "10"
    },
    {
      "id": "adem_eijas",
      "name_arb": "آدم بْن أَبي إياس العسقلاني ",
      "val": "10"
    },
    {
      "id": "ahmed_abdullah_junus",
      "name_arb": "أَحْمَد بْن عَبد اللَّهِ بْن يونس اليربوعي",
      "val": "10"
    },
    {
      "id": "ahmed_amr",
      "name_arb": "أَحْمَد بْن عَمْرو بْن السرح المِصْرِي",
      "val": "10"
    },
    {
      "id": "ahmed_ebekr",
      "name_arb": "أَحْمَد بن أَبي بَكْر بْن الحارث القرشي الزُّهْرِيّ المدني",
      "val": "30"
    },
    {
      "id": "ahmed_ehavari",
      "name_arb": "أَحْمَد بْن أَبي الحواري الدمشقي",
      "val": "10"
    },
    {
      "id": "ahmed_eshuajb",
      "name_arb": "أَحْمَد بْن أَبي شعيب الحراني ",
      "val": "10"
    },
    {
      "id": "ahmed_ezher",
      "name_arb": "أَحْمَد بن الأَزْهَر بن منيع أَبُو الأَزْهَر النَّيْسَابُورِيّ",
      "val": "30"
    },
    {
      "id": "ahmed_ibrahim_ertah",
      "name_arb": "أَحْمَد بن إِبْرَاهِيم بن مُحَمَّد ابْن أَبي أرطاة الدمشقي",
      "val": "30"
    },
    {
      "id": "ahmed_ibrahim_esdi",
      "name_arb": "أَحْمَد بن إِبْرَاهِيم بن فيل الأسدي",
      "val": "30"
    },
    {
      "id": "ahmed_ibrahim_halid",
      "name_arb": "أَحْمَد بن إِبْرَاهِيم بن خالد الموصلي",
      "val": "30"
    },
    {
      "id": "ahmed_ibrahim_kethir",
      "name_arb": "أَحْمَد بن إِبْرَاهِيم بن كثير العبدي",
      "val": "30"
    },
    {
      "id": "ahmed_muhamed_thabit",
      "name_arb": "أَحْمَد بْن مُحَمَّد بْن ثَابِت الخزاعي المروزي",
      "val": "10"
    },
    {
      "id": "ahmed_nasr_malik",
      "name_arb": "أَحْمَد بْن نصر بْن مَالِك الخزاعي الشهيد ",
      "val": "10"
    },
    {
      "id": "ala_abdxhebar",
      "name_arb": "العلاء بْن عَبْد الْجَبَّارِ العطار ",
      "val": "10"
    },
    {
      "id": "ali_asim",
      "name_arb": "علي بْن عاصم الواسطي ",
      "val": "10"
    },
    {
      "id": "amir_ismail",
      "name_arb": "عامر بْن إِسْمَاعِيل الْبَغْدَادِيّ",
      "val": "10"
    },
    {
      "id": "behz_esed",
      "name_arb": "بهز بْن أسد العمي البَصْرِيّ",
      "val": "10"
    },
    {
      "id": "bekr_abdrrahman",
      "name_arb": "بكر بْن عَبْد الرَّحْمَنِ الكوفي القاضي ",
      "val": "10"
    },
    {
      "id": "bukejr_muhamed",
      "name_arb": "بكير بْن مُحَمَّد بْن أسماء",
      "val": "10"
    },
    {
      "id": "dahak_mahled",
      "name_arb": "الضحاك بْن مخلد أَبِي عاصم النبيل",
      "val": "10"
    },
    {
      "id": "ejub_muktib",
      "name_arb": "أيوب المكتب ",
      "val": "10"
    },
    {
      "id": "enes_ijad",
      "name_arb": "أنس بْن عياض الليثي",
      "val": "10"
    },
    {
      "id": "esbat_muhamed",
      "name_arb": "أسباط بْن مُحَمَّد القرشي ",
      "val": "10"
    },
    {
      "id": "ferexh_fedale",
      "name_arb": "فرج بْن فضالة الشامي ",
      "val": "10"
    },
    {
      "id": "habib_habib_kufi",
      "name_arb": "حبيب بْن حبيب الكوفي أخي حمزة بْن حبيب الزيات القارئ",
      "val": "10"
    },
    {
      "id": "hafs_gijath",
      "name_arb": "حفص ابن غِيَاث النخعي القاضي ",
      "val": "10"
    },
    {
      "id": "hakem_dhahir",
      "name_arb": "الحكم بْن ظهير الفزاري",
      "val": "10"
    },
    {
      "id": "hakem_sinan",
      "name_arb": "الحكم بْن سنان الباهلي القربي",
      "val": "10"
    },
    {
      "id": "halef_halife",
      "name_arb": "خلف بْن خليفة",
      "val": "10"
    },
    {
      "id": "halid_amr",
      "name_arb": "خالد بْن عَمْرو السلفي ",
      "val": "10"
    },
    {
      "id": "halid_mahled",
      "name_arb": "خالد بْن مخلد القطواني",
      "val": "10"
    },
    {
      "id": "hamad_jahja",
      "name_arb": "حماد بن يحيى البلخي",
      "val": "10"
    },
    {
      "id": "hamad_malik",
      "name_arb": "حَمَّاد بْن مَالِك الأشجعي الحرستاني",
      "val": "10"
    },
    {
      "id": "hamad_usame",
      "name_arb": "حَمَّاد بْن أسامة",
      "val": "10"
    },
    {
      "id": "hamad_zejd",
      "name_arb": "حماد بْن زَيْد",
      "val": "10"
    },
    {
      "id": "abas_abdrrahman",
      "name_arb": "الْعَبَّاس بْن عبد الرحمن بن الوليد ابن نجيح القرشي",
      "val": "10"
    },
    {
      "id": "abdhamid_bekar",
      "name_arb": "عبد الحميد بْن بكار البيروتي",
      "val": "10"
    },
    {
      "id": "hasen_isa",
      "name_arb": "الحسن بْنُ عيسى بْن ماسرجس النَّيْسَابُورِيّ مولى ابْن المبارك",
      "val": "10"
    },
    {
      "id": "haxhaxh_muhamed",
      "name_arb": "حجاج بْن مُحَمَّد المصيصي الأَعور ",
      "val": "10"
    },
    {
      "id": "hejthem_xhemil",
      "name_arb": "الهيثم بْن جميل الأنطاكي ",
      "val": "10"
    },
    {
      "id": "hisham_abdmelik",
      "name_arb": "هشام بْن عَبد المَلِك الطيالسي",
      "val": "10"
    },
    {
      "id": "hisham_amar",
      "name_arb": "هشام بْن عمار الدمشقي",
      "val": "10"
    },
    {
      "id": "hudje_abdvehab",
      "name_arb": "هدية بْن عبد الوهاب المروزي",
      "val": "10"
    },
    {
      "id": "hushejm_beshir",
      "name_arb": "هشيم بْن بشير الواسطي",
      "val": "10"
    },
    {
      "id": "ibrahim_abdullah_ala",
      "name_arb": "إبراهيم بْن عَبد اللَّهِ بْن العلاء بْن زبر الربعي",
      "val": "10"
    },
    {
      "id": "ibrahim_hakem_eban",
      "name_arb": "إِبْرَاهِيم بْن الحكم بْن أبان العدني",
      "val": "10"
    },
    {
      "id": "ibrahim_mehdi",
      "name_arb": "إِبْرَاهِيم بْن مهدي المصيصي",
      "val": "10"
    },
    {
      "id": "ibrahim_muhamed_jusuf",
      "name_arb": "إبراهيم بْن مُحَمَّد بْن يُوسُف الفريابي ",
      "val": "10"
    },
    {
      "id": "ibrahim_muhamed_kureshi",
      "name_arb": "إِبْرَاهِيم بْن مُحَمَّد بْن عَبد اللَّهِ القرشي",
      "val": "10"
    },
    {
      "id": "ibrahim_mundhir",
      "name_arb": "إبراهيم بْن المنذر الحزامي",
      "val": "10"
    },
    {
      "id": "ibrahim_sad_zuhri",
      "name_arb": "إِبْرَاهِيم بْن سعد بْن إِبْرَاهِيم بْن عَبْد الرَّحْمَنِ بْن عوف الزُّهْرِيّ المدني",
      "val": "10"
    },
    {
      "id": "ibrahim_seid",
      "name_arb": "إِبْرَاهِيم بْن سَعِيد الجوهري",
      "val": "10"
    },
    {
      "id": "ibrahim_sulejman_muedib",
      "name_arb": "إبراهيم بْن سُلَيْمان أَبِي إِسْمَاعِيل المؤدب",
      "val": "10"
    },
    {
      "id": "isa_sulejman",
      "name_arb": "عيسى بْن سُلَيْمان الحجازي",
      "val": "10"
    },
    {
      "id": "ishak_ibrahim_jezid",
      "name_arb": "إسحاق بْن إِبْرَاهِيم بْن يزيد الدمشقي الفراديسي",
      "val": "10"
    },
    {
      "id": "ishak_jusuf",
      "name_arb": "إسحاق بْن يُوسُف الأزرق ",
      "val": "10"
    },
    {
      "id": "ishak_mensur",
      "name_arb": "إسحاق بْن مَنْصُور السلولي",
      "val": "10"
    },
    {
      "id": "ishak_seid_arkon",
      "name_arb": "إسحاق بْن سَعِيد بن الا ركون الدمشقي",
      "val": "10"
    },
    {
      "id": "ishak_sulejman",
      "name_arb": "إسحاق بْن سُلَيْمان الرازي ",
      "val": "10"
    },
    {
      "id": "ismail_abdkerim",
      "name_arb": "إِسْمَاعِيل بْن عبد الكريم بْن معقل الصنعاني",
      "val": "10"
    },
    {
      "id": "ismail_ibrahim_mamer",
      "name_arb": "إِسْمَاعِيل بْن إِبْرَاهِيم بْن مَعْمَر الهذلي القَطِيعِيّ",
      "val": "10"
    },
    {
      "id": "ismail_ibrahim_uleje",
      "name_arb": "إسماعيل بْن إِبْرَاهِيم بْن مقسم الأسدي المعروف بابن علية",
      "val": "10"
    },
    {
      "id": "ismail_omer",
      "name_arb": "إِسْمَاعِيل بْن عُمَر الواسطي",
      "val": "10"
    },
    {
      "id": "ismail_ubejd",
      "name_arb": "إسماعيل ابن عُبَيد بْن أَبي كريمة الحراني",
      "val": "10"
    },
    {
      "id": "jahja_adem",
      "name_arb": "يحيى بْن آدم",
      "val": "10"
    },
    {
      "id": "jakub_humejd_medeni",
      "name_arb": "يعقوب بْن حميد بْن كاسب المدني",
      "val": "10"
    },
    {
      "id": "jakub_ibrahim_zuhri",
      "name_arb": "يعقوب بْن إِبْرَاهِيم بْن سعد الزُّهْرِيّ",
      "val": "10"
    },
    {
      "id": "jala_ubejd_tanafisi",
      "name_arb": "يَعْلَى بْن عُبَيد الطنافسي",
      "val": "10"
    },
    {
      "id": "jezid_ehakim",
      "name_arb": "يزيد بْن أَبي حكيم العدني",
      "val": "10"
    },
    {
      "id": "jezid_halid",
      "name_arb": "يزيد بْن خالد بْن موهب الهمداني الرملي ",
      "val": "10"
    },
    {
      "id": "jezid_harun",
      "name_arb": "يزيد بْن هارون",
      "val": "10"
    },
    {
      "id": "jezid_zurej",
      "name_arb": "يزيد بْن زريع",
      "val": "10"
    },
    {
      "id": "junus_muhamed_muedib",
      "name_arb": "يونس بْن مُحَمَّد المؤدب",
      "val": "10"
    },
    {
      "id": "jusuf_atije",
      "name_arb": "يوسف بْن عطية الصفار البَصْرِيّ",
      "val": "10"
    },
    {
      "id": "kethir_jezid",
      "name_arb": "كثير بْن يزيد القنسريني",
      "val": "10"
    },
    {
      "id": "kurejsh_enes",
      "name_arb": "قريش بْن أنس البَصْرِيّ",
      "val": "10"
    },
    {
      "id": "kutejbe_seid",
      "name_arb": "قتيبة ابن سَعِيد الثقفي البلخي",
      "val": "10"
    },
    {
      "id": "mahbub_musa",
      "name_arb": "محبوب بْن مُوسَى الأنطاكي الفراء",
      "val": "10"
    },
    {
      "id": "malik_seir",
      "name_arb": "مالك بْن سعير ",
      "val": "10"
    },
    {
      "id": "mehdi_xhafer",
      "name_arb": "مهدي بْن جَعْفَر الرملي",
      "val": "10"
    },
    {
      "id": "mervan_muhamed",
      "name_arb": "مروان بْن مُحَمَّد الدمشقي المعروف بالطاطري ",
      "val": "10"
    },
    {
      "id": "muafa_sulejman",
      "name_arb": "المعافى بْن سُلَيْمان الرسعني",
      "val": "10"
    },
    {
      "id": "muala_mensur",
      "name_arb": "معلى بْن مَنْصُور الرازي ",
      "val": "10"
    },
    {
      "id": "muavije_abdkerim",
      "name_arb": "معاوية بْن عبد الكريم الثقفي المعروف بالضال",
      "val": "10"
    },
    {
      "id": "mubeshir_ismail",
      "name_arb": "مبشر بْن إسماعيل الحلبي ",
      "val": "10"
    },
    {
      "id": "muhamed_abdullah_bekar",
      "name_arb": "مُحَمَّد بْن عَبد اللَّهِ بْن بكار القرشي الدمشقي",
      "val": "10"
    },
    {
      "id": "muhamed_abdullah_ensari",
      "name_arb": "محمد بْن عَبد اللَّهِ الأَنْصارِيّ ",
      "val": "10"
    },
    {
      "id": "muhamed_adem_mesisi",
      "name_arb": "محمد بْن آدم المصيصي",
      "val": "10"
    },
    {
      "id": "muhamed_aidh",
      "name_arb": "محمد بْن عائذ القرشي الدمشقي",
      "val": "10"
    },
    {
      "id": "muhamed_bilal",
      "name_arb": "محمد بْن بلال البَصْرِيّ",
      "val": "10"
    },
    {
      "id": "muhamed_bishr_abdi",
      "name_arb": "محمد بْن بشر العبدي",
      "val": "10"
    },
    {
      "id": "muhamed_fadl_sedus",
      "name_arb": "مُحَمَّد بْن الفضل السدوسي",
      "val": "10"
    },
    {
      "id": "mahmud_halid",
      "name_arb": "محمود بْن خالد السلمي الدمشقي",
      "val": "10"
    },
    {
      "id": "muhamed_isa_taba",
      "name_arb": "محمد ابن عيسى ابن الطباع ",
      "val": "10"
    },
    {
      "id": "muhamed_ismail_basri",
      "name_arb": "محمد بْن إِسْمَاعِيل بْن أَبي سمينة البَصْرِيّ",
      "val": "10"
    },
    {
      "id": "muhamed_ismail_efudejk",
      "name_arb": "محمد بْن إِسْمَاعِيل بْن أَبي فديك ",
      "val": "10"
    },
    {
      "id": "muhamed_jezid_meki",
      "name_arb": "محمد بْن يزيد بْن خنيس المكي",
      "val": "10"
    },
    {
      "id": "muhamed_jezid_tarsusi",
      "name_arb": "محمد بْن يزيد الطرسوسي",
      "val": "10"
    },
    {
      "id": "muhamed_jusuf_firjabi",
      "name_arb": "محمد بْن يُوسُف الفريابي ",
      "val": "10"
    },
    {
      "id": "muhamed_kasim_harrani",
      "name_arb": "محمد بْن الْقَاسِم الحراني",
      "val": "10"
    },
    {
      "id": "muhamed_kethir_mesisi",
      "name_arb": "محمد بْن كثير المصيصي ",
      "val": "10"
    },
    {
      "id": "muhamed_kudame_mesisi",
      "name_arb": "محمد بْن قدامة بْن أعين المصيصي",
      "val": "10"
    },
    {
      "id": "muhamed_mukatil",
      "name_arb": "محمد بْن مقاتل العباداني",
      "val": "10"
    },
    {
      "id": "muhamed_musafa_mesisi",
      "name_arb": "محمد بْن مصفى الحمصي",
      "val": "10"
    },
    {
      "id": "muhamed_omer",
      "name_arb": "محمد ابن عُمَر الكِلابي ",
      "val": "10"
    },
    {
      "id": "muhamed_othman",
      "name_arb": "مُحَمَّد بْن عثمان التنوخي الكفرسوسي ",
      "val": "10"
    },
    {
      "id": "muhamed_selam_entaki",
      "name_arb": "محمد ابن سلام الأنطاكي ثم المنبجي",
      "val": "10"
    },
    {
      "id": "muhamed_shurahbil",
      "name_arb": "محمد بْن شرحبيل الأَنْبارِيّ",
      "val": "10"
    },
    {
      "id": "muhamed_sulejman",
      "name_arb": "محمد بْن سُلَيْمان بْن أَبي داود الحراني",
      "val": "10"
    },
    {
      "id": "muhamed_thabit",
      "name_arb": "محمد بْن ثَابِت العبدي ",
      "val": "10"
    },
    {
      "id": "muhamed_ubejd",
      "name_arb": "محمد بْن عُبَيد الطنافسي ",
      "val": "10"
    },
    {
      "id": "musa_ejub_nasibi",
      "name_arb": "موسى بْن أيوب النصيبي",
      "val": "10"
    },
    {
      "id": "musa_ismail",
      "name_arb": "مُوسَى بْن إِسْمَاعِيل التبوذكي",
      "val": "10"
    },
    {
      "id": "musejeb_vadih",
      "name_arb": "المُسَيَّب بْن واضح الحمصي",
      "val": "10"
    },
    {
      "id": "nasih_ala",
      "name_arb": "ناصح بْن العلاء",
      "val": "10"
    },
    {
      "id": "nasr_muhamed",
      "name_arb": "نصر بْن مُحَمَّد بْن سُلَيْمان ابن أَبي ضمرة الحمصي",
      "val": "10"
    },
    {
      "id": "nuh_kajs",
      "name_arb": "نوح بْن قيس الحداني",
      "val": "10"
    },
    {
      "id": "omer_hafs_bezaz",
      "name_arb": "عَمْرو بن حفص ابن شليلة الثقفي البزاز",
      "val": "10"
    },
    {
      "id": "omer_hafs_gijath",
      "name_arb": "عُمَر بْن حفص ابن غِيَاث النخعي ",
      "val": "10"
    },
    {
      "id": "omer_jezid",
      "name_arb": "عُمَر بْن يزيد السياري",
      "val": "10"
    },
    {
      "id": "omer_othman_himsi",
      "name_arb": "عَمْرو بْن عثمان بْن سَعِيد بْن كثير بْن دينار الحمصي",
      "val": "10"
    },
    {
      "id": "omer_othman_reki",
      "name_arb": "عَمْرو بْن عثمان الرَّقِّيّ ",
      "val": "10"
    },
    {
      "id": "omer_ubejd",
      "name_arb": "عُمَر بْن عُبَيد الطنافسي",
      "val": "10"
    },
    {
      "id": "rebii_nafii",
      "name_arb": "الربيع بْن نَافِع الحلبي",
      "val": "10"
    },
    {
      "id": "rejhan_seid",
      "name_arb": "ريحان بْن سَعِيد الناجي البَصْرِيّ ",
      "val": "10"
    },
    {
      "id": "reuh_ubade",
      "name_arb": "روح بْن عبادة",
      "val": "10"
    },
    {
      "id": "ribij_ibrahim",
      "name_arb": "ربعي بن إبراهيم بن علية ",
      "val": "10"
    },
    {
      "id": "safvan_isa",
      "name_arb": "صفوان بْن عيسى الزُّهْرِيّ ",
      "val": "10"
    },
    {
      "id": "salih_omer",
      "name_arb": "صالح بْن عُمَر الواسطي",
      "val": "10"
    },
    {
      "id": "seid_abdrrahman",
      "name_arb": "سَعِيد بْن عَبْد الرَّحْمَنِ الجمحي",
      "val": "10"
    },
    {
      "id": "seid_abdxhebar",
      "name_arb": "سَعِيد بْن عَبْد الْجَبَّارِ الزبيدي الحمصي",
      "val": "10"
    },
    {
      "id": "seid_amir",
      "name_arb": "سَعِيد بْن عامر الضبعي ",
      "val": "10"
    },
    {
      "id": "seid_hafs",
      "name_arb": "سَعِيد بْن حفص النفيلي الحراني",
      "val": "10"
    },
    {
      "id": "sejf_harun",
      "name_arb": "سيف بْن هارون البرجمي",
      "val": "10"
    },
    {
      "id": "selam_selim",
      "name_arb": "سلام بْن سليم الحنفي",
      "val": "10"
    },
    {
      "id": "selam_sulejman",
      "name_arb": "سلام ابن سُلَيْمان القارئ",
      "val": "10"
    },
    {
      "id": "shebabe_sevar",
      "name_arb": "شبابة بْن سوار الفزاري",
      "val": "10"
    },
    {
      "id": "sherik_abdullah",
      "name_arb": "شَرِيك بْن عَبد اللَّهِ النخعي القاضي",
      "val": "10"
    },
    {
      "id": "shuxha_velid",
      "name_arb": "شجاع بْن الوليد بْن قيس السكوني",
      "val": "10"
    },
    {
      "id": "subej_eshath",
      "name_arb": "الصبي بن الاشعث ابن سالم السلولي",
      "val": "10"
    },
    {
      "id": "sulejman_abdrrahman",
      "name_arb": "سُلَيْمان بْن عَبْد الرَّحْمَنِ الدمشقي",
      "val": "10"
    },
    {
      "id": "sulejman_harb",
      "name_arb": "سُلَيْمان بْن حرب",
      "val": "10"
    },
    {
      "id": "sulejman_seleme",
      "name_arb": "سُلَيْمان بْن سَلَمَة الخبائري ",
      "val": "10"
    },
    {
      "id": "suvejd_seid",
      "name_arb": "سويد بْن سَعِيد الحدثاني ",
      "val": "10"
    },
    {
      "id": "talk_ganam",
      "name_arb": "طلق ابن غنام النخعي ",
      "val": "10"
    },
    {
      "id": "ubejdullah_musa",
      "name_arb": "عُبَيد الله بْن مُوسَى العبسي ",
      "val": "10"
    },
    {
      "id": "vedah_abdullah",
      "name_arb": "الوضاح بْن عَبد الله اليشكري الواسطي",
      "val": "10"
    },
    {
      "id": "vehb_bejan",
      "name_arb": "وهب بْن بيان الواسطي",
      "val": "10"
    },
    {
      "id": "vehb_bekije",
      "name_arb": "وهب بْن بقية الواسطي",
      "val": "10"
    },
    {
      "id": "vehb_xherir",
      "name_arb": "وهب بْن جرير بْن حازم ",
      "val": "10"
    },
    {
      "id": "vekii_xherrah",
      "name_arb": "وكيع بْن الجراح",
      "val": "10"
    },
    {
      "id": "xhafer_sulejman",
      "name_arb": "جعفر ابن سُلَيْمان الضبعي",
      "val": "10"
    },
    {
      "id": "xharud_jezid",
      "name_arb": "الجارود بْن يزيد العامري النَّيْسَابُورِيّ",
      "val": "10"
    },
    {
      "id": "xherir_abdhamid",
      "name_arb": "جرير بن عبد الحميد الضبي الرازي",
      "val": "10"
    },
    {
      "id": "zejd_habab",
      "name_arb": "زيد بْن الحباب ",
      "val": "10"
    },
    {
      "id": "zejd_jahja",
      "name_arb": "زيد بْن يحيى بْن عُبَيد الدمشقي",
      "val": "10"
    },
    {
      "id": "zuhejr_abad",
      "name_arb": "زهير بْن عباد الرؤاسي",
      "val": "10"
    },
    {
      "id": "zuhejr_neim",
      "name_arb": "زهير بْن نعيم بْن داود الطيالسي ",
      "val": "10"
    },
    {
      "id": "ahmed_ishak_buhari",
      "name_arb": "أَحْمَد بن إسحاق بن الْحُصَيْن السلمي البخاري",
      "val": "30"
    },
    {
      "id": "ahmed_ishak_basri",
      "name_arb": "أَحْمَد بن إسحاق بن زَيْد بن الحضرمي البَصْرِيّ",
      "val": "30"
    },
    {
      "id": "ahmed_ishak_ehvazi",
      "name_arb": "أَحْمَد بن إسحاق بن عيسى الأهوازي البزاز",
      "val": "30"
    },
    {
      "id": "ahmed_ismail_medeni",
      "name_arb": "أَحْمَد بن إِسْمَاعِيل بن مُحَمَّد القرشي السهمي المدني",
      "val": "30"
    },
    {
      "id": "ahmed_ishkab",
      "name_arb": "أَحْمَد بن إشكاب الحضرمي الصفار الكوفي",
      "val": "30"
    },
    {
      "id": "ahmed_ejub",
      "name_arb": "أَحْمَد بن أيوب بن راشد الضبي الشعيري البَصْرِيّ",
      "val": "30"
    },
    {
      "id": "ahmed_budejl",
      "name_arb": "أَحْمَد بن بديل بن قريش اليامي الكوفي",
      "val": "30"
    },
    {
      "id": "ahmed_beshir",
      "name_arb": "أَحْمَد بن بشير القرشي المخزومي الكوفي",
      "val": "30"
    },
    {
      "id": "ahmed_bekar",
      "name_arb": "أَحْمَد بن بكار بن أَبي ميمونة القرشي الأُمَوِي الحراني",
      "val": "30"
    },
    {
      "id": "ahmed_thabit",
      "name_arb": "أَحْمَد بن ثَابِت الجحدري البَصْرِيّ",
      "val": "30"
    },
    {
      "id": "ahmed_xhafer",
      "name_arb": "أَحْمَد بن جَعْفَر المعقري البزاز",
      "val": "30"
    },
    {
      "id": "ahmed_xhenab",
      "name_arb": "أَحْمَد بن جناب بن المغيرة المصيصي الحدثي",
      "val": "30"
    },
    {
      "id": "ahmed_xhevas",
      "name_arb": "أَحْمَد بن جواس الحنفي الكوفي",
      "val": "30"
    },
    {
      "id": "ahmed_haxhaxh",
      "name_arb": "أَحْمَد بن الحجاج البكري الذهلي الشَّيْبَانِيّ المروزي",
      "val": "30"
    },
    {
      "id": "othman_omer",
      "name_arb": "عثمان بن عُمَربن فارس ",
      "val": "10"
    },
    {
      "id": "amr_asim",
      "name_arb": "عَمْرو بْن عاصم الكِلابي ",
      "val": "10"
    },
    {
      "id": "jahja_hamad",
      "name_arb": "يحيى بْن حماد الشيباني ",
      "val": "10"
    },
    {
      "id": "hamad_seleme",
      "name_arb": "حَمَّاد بْن سَلَمَة",
      "val": "10"
    },
    {
      "id": "halil_merre",
      "name_arb": "الخليل بْن مرة",
      "val": "10"
    },
    {
      "id": "abdullah_hasan",
      "name_arb": "عبد الله بْن حسان العنبري",
      "val": "10"
    },
    {
      "id": "abdullah_arade",
      "name_arb": "عبد الله بْن عرادة الشَّيْبَانِيّ",
      "val": "10"
    },
    {
      "id": "abdaziz_muhtar",
      "name_arb": "عبد العزيز بْن المختار ",
      "val": "10"
    },
    {
      "id": "abdvahid_zijad",
      "name_arb": "عبد الواحد بْن زياد",
      "val": "10"
    },
    {
      "id": "ikrime_amar",
      "name_arb": "عكرمة بْن عمار اليمامي",
      "val": "10"
    },
    {
      "id": "imran_halid",
      "name_arb": "عِمْران بْن خالد الخزاعي",
      "val": "10"
    },
    {
      "id": "hemam_jahja",
      "name_arb": "همام بْن يحيى ",
      "val": "10"
    },
    {
      "id": "vuhejb_halid",
      "name_arb": "وهيب بْن خالد ",
      "val": "10"
    },
    {
      "id": "jahja_seid",
      "name_arb": "يحى بْن سَعِيد القطان",
      "val": "10"
    },
    {
      "id": "haxhaxh_nusajr",
      "name_arb": "حجاج بْن نصير الفساطيطي",
      "val": "10"
    },
    {
      "id": "halad_jahja",
      "name_arb": "خلاد بْن يحيى السلمي",
      "val": "10"
    },
    {
      "id": "amir_mudrik",
      "name_arb": "عامر بْن مدرك الحارثي",
      "val": "10"
    },
    {
      "id": "abdullah_serij",
      "name_arb": "عبد الله بْن السري الأنطاكي",
      "val": "10"
    },
    {
      "id": "abdullah_jezid",
      "name_arb": "عبد الله بْن يزيد أَبِي عَبْد الرَّحْمَنِ الْمُقْرِئ",
      "val": "10"
    },
    {
      "id": "muhamed_abdullah_zubejri",
      "name_arb": "محمد بْن عَبد اللَّهِ بْن الزبير أَبِي أَحْمَد الزبيري ",
      "val": "10"
    },
    {
      "id": "musa_davud",
      "name_arb": "موسى بن داود الضبي",
      "val": "10"
    },
    {
      "id": "jala_abad",
      "name_arb": "يَعْلَى بْن عباد الكِلابي",
      "val": "10"
    },
    {
      "id": "sad_seid",
      "name_arb": "سعد بْن سَعِيد بْن أَبي سَعِيد المقبري ",
      "val": "10"
    },
    {
      "id": "abdrrahman_ezinad",
      "name_arb": "عبد الرحمن بْن أَبي الزناد",
      "val": "10"
    },
    {
      "id": "abdaziz_imran",
      "name_arb": "عبد العزيز بْن عِمْران بن عبد العزيز الزُّهْرِيّ",
      "val": "10"
    },
    {
      "id": "kethir_xhafer",
      "name_arb": "كثير بْن جَعْفَر بْن أَبي كثير",
      "val": "10"
    },
    {
      "id": "muslim_halid",
      "name_arb": "مسلم بْن خالد الزنجي",
      "val": "10"
    },
    {
      "id": "musab_abdullah",
      "name_arb": "مصعب بْن عَبد اللَّهِ الزبيري",
      "val": "10"
    },
    {
      "id": "ismail_ibrahim_tejmi",
      "name_arb": "إِسْمَاعِيل بْن إِبْرَاهِيم التَّيْمِيّ الأحول",
      "val": "10"
    },
    {
      "id": "rifaa_ijas",
      "name_arb": "رفاعة بْن إياس بْن نذير الضبي",
      "val": "10"
    },
    {
      "id": "abdrrahman_abdmelik",
      "name_arb": "عبد الرحمن بْن عَبد المَلِك بْن أبجر",
      "val": "10"
    },
    {
      "id": "abdrrahman_muhamed_muharibi",
      "name_arb": "عبد الرحمن بْن مُحَمَّد المحاربي",
      "val": "10"
    },
    {
      "id": "abdrrahim_sulejman",
      "name_arb": "عبد الرحيم بْن سُلَيْمان الرازي",
      "val": "10"
    },
    {
      "id": "abdselam_harb",
      "name_arb": "عبد السلام بْن حرب الملائي ",
      "val": "10"
    },
    {
      "id": "ali_abis",
      "name_arb": "علي بْن عابس",
      "val": "10"
    },
    {
      "id": "kasim_malik",
      "name_arb": "القاسم بْن مَالِك المزني ",
      "val": "10"
    },
    {
      "id": "jahja_jala",
      "name_arb": "يحيى بْن يَعْلَى الأَسلميّ",
      "val": "10"
    },
    {
      "id": "ebekr_ajash",
      "name_arb": "أبي بَكْر بْن عياش",
      "val": "10"
    },
    {
      "id": "sufjan_habib",
      "name_arb": "سفيان بْن حبيب",
      "val": "10"
    },
    {
      "id": "sehl_eslem",
      "name_arb": "سهل بْن أسلم",
      "val": "10"
    },
    {
      "id": "abdala_abdala",
      "name_arb": "عبد الاعلى بن عبد الاعلى",
      "val": "10"
    },
    {
      "id": "abdvarith_seid",
      "name_arb": "عبد الوارث بْن سَعِيد",
      "val": "10"
    },
    {
      "id": "aubid_eimran",
      "name_arb": "عوبد بْن أَبي عِمْران الجوني",
      "val": "10"
    },
    {
      "id": "mesleme_alkame",
      "name_arb": "مسلمة بْن عَلْقَمَة المازني",
      "val": "10"
    },
    {
      "id": "ibrahim_ujejne",
      "name_arb": "إِبْرَاهِيم بْن عُيَيْنَة بْن أَبي عِمْران الهلالي",
      "val": "10"
    },
    {
      "id": "xhabir_nuh",
      "name_arb": "جابر بْن نوح بْن جَابِر الحماني",
      "val": "10"
    },
    {
      "id": "abdullah_idris",
      "name_arb": "عبد الله بْن إدريس الأَودِيّ",
      "val": "10"
    },
    {
      "id": "abdullah_mejmun_tahevi",
      "name_arb": "عبد الله بْن ميمون الطهوي",
      "val": "10"
    },
    {
      "id": "utham_ali",
      "name_arb": "عثام بْن علي العامري",
      "val": "10"
    },
    {
      "id": "isa_rashid",
      "name_arb": "عيسى بْن راشد",
      "val": "10"
    },
    {
      "id": "muhamed_hazim",
      "name_arb": "محمد بْن خازم",
      "val": "10"
    },
    {
      "id": "mufedal_salih",
      "name_arb": "مفضل بْن صَالِح الأسدي",
      "val": "10"
    },
    {
      "id": "jahja_isa",
      "name_arb": "يحيى بْن عيسى الرملي",
      "val": "10"
    },
    {
      "id": "ismail_ehalid",
      "name_arb": "إِسْمَاعِيل بْن أَبي خالد",
      "val": "10"
    },
    {
      "id": "hafs_emensur",
      "name_arb": "أبي الخطاب حَفْص بْن أَبي مَنْصُور الكوفي",
      "val": "10"
    },
    {
      "id": "seid_earube",
      "name_arb": "سَعِيد بْن أَبي عَرُوبَة",
      "val": "10"
    },
    {
      "id": "sulejman_mihran",
      "name_arb": "سُلَيْمان بْن مهران الأَعْمَش",
      "val": "10"
    },
    {
      "id": "shebib_bishr",
      "name_arb": "شبيب بْن بشر ",
      "val": "10"
    },
    {
      "id": "shube_haxhaxh",
      "name_arb": "شعبة بْن الحجاج",
      "val": "10"
    },
    {
      "id": "abdullah_shubrume",
      "name_arb": "عبد الله بْن شبرمة ",
      "val": "10"
    },
    {
      "id": "ubejdullah_omer",
      "name_arb": "عُبَيد الله بْن عُمَر ",
      "val": "10"
    },
    {
      "id": "alil_bexheli",
      "name_arb": "عليل البجلي",
      "val": "10"
    },
    {
      "id": "omer_hamze",
      "name_arb": "عُمَر بْن حمزة العُمَري ",
      "val": "10"
    },
    {
      "id": "avane_hakem",
      "name_arb": "عوانة بْن الحكم الكلبي",
      "val": "10"
    },
    {
      "id": "isa_mejmun",
      "name_arb": "عيسى بْن ميمون المدني ",
      "val": "10"
    },
    {
      "id": "muxhalid_seid",
      "name_arb": "مجالد بْن سَعِيد ",
      "val": "10"
    },
    {
      "id": "muhamed_eismail",
      "name_arb": "محمد بْن أَبي إِسْمَاعِيل",
      "val": "10"
    },
    {
      "id": "misar_kidam",
      "name_arb": "مسعر بن كدام",
      "val": "10"
    },
    {
      "id": "harun_antere",
      "name_arb": "هارون بْن عنترة",
      "val": "10"
    },
    {
      "id": "hisham_hashim",
      "name_arb": "هاشم بْن هاشم الزُّهْرِيّ ",
      "val": "10"
    },
    {
      "id": "hisham_hasan",
      "name_arb": "هشام بْن حسان",
      "val": "10"
    },
    {
      "id": "hisham_urve",
      "name_arb": "هشام بْن عروة",
      "val": "10"
    },
    {
      "id": "jahja_sulejman",
      "name_arb": "أبي البلاد يحيى بْن سُلَيْمان الكوفي",
      "val": "10"
    },
    {
      "id": "bishr_serij",
      "name_arb": "بشر بْن السري",
      "val": "10"
    },
    {
      "id": "beshir_abdullah",
      "name_arb": "بشير بْن عَبد اللَّهِ",
      "val": "10"
    },
    {
      "id": "bekar_emejmune",
      "name_arb": "بكار بْن أَبي ميمونة",
      "val": "10"
    },
    {
      "id": "xhafer_aun",
      "name_arb": "جعفر بْن عون العُمَري",
      "val": "10"
    },
    {
      "id": "abdhamid_abdrrahman",
      "name_arb": "أبي يحيى عبد الحميد بْن عَبْد الرَّحْمَنِ الحماني",
      "val": "10"
    },
    {
      "id": "muhamed_seleme",
      "name_arb": "محمد بْن سَلَمَة الحراني ",
      "val": "10"
    },
    {
      "id": "muhamed_fudajl",
      "name_arb": "محمد بْن فضيل بْن غزوان الضبي",
      "val": "10"
    },
    {
      "id": "mahled_jezid",
      "name_arb": "مخلد بْن يزيد الحراني ",
      "val": "10"
    },
    {
      "id": "vehb_ismail",
      "name_arb": "وهب بْن إِسْمَاعِيل الأسدي",
      "val": "10"
    },
    {
      "id": "eseid_mbhashim",
      "name_arb": "أبي سَعِيد مولى بني هاشم ",
      "val": "10"
    },
    {
      "id": "abdullah_vakid",
      "name_arb": "عَبد اللَّهِ بْن واقد الحراني",
      "val": "10"
    },
    {
      "id": "husejn_zejd",
      "name_arb": "حسين بْن زَيْد بْن علي ابن الحسين بْن علي بْن أَبي طالب",
      "val": "10"
    },
    {
      "id": "salih_kidame",
      "name_arb": "صالح بْن قدامة بْن إِبْرَاهِيم بْن مُحَمَّد بْن حاطب الجمحي",
      "val": "10"
    },
    {
      "id": "asim_suvejd",
      "name_arb": "عاصم بْن سويد الأَنْصارِيّ القبائي",
      "val": "10"
    },
    {
      "id": "abdrrahman_zejd",
      "name_arb": "عبد الرحمن بْن زَيْد بْن أسلم ",
      "val": "10"
    },
    {
      "id": "abdaziz_ehazim",
      "name_arb": "عبد العزيز بْن أَبي حازم المدني ",
      "val": "10"
    },
    {
      "id": "abdaziz_muhamed",
      "name_arb": "عبد العزيز ابن مُحَمَّد الدَّراوَرْدِيّ ",
      "val": "10"
    },
    {
      "id": "abdmuhejmin_abas",
      "name_arb": "عبد المهيمن بْن عَبَّاس بْن سهل ابن سعد الساعدي ",
      "val": "10"
    },
    {
      "id": "ataf_halid",
      "name_arb": "العطاف بْن خالد المخزومي",
      "val": "10"
    },
    {
      "id": "omer_talha",
      "name_arb": "عُمَر بْن طلحة بْن عَلْقَمَة بْن وقاص الليثي",
      "val": "10"
    },
    {
      "id": "imran_abdaziz",
      "name_arb": "أبي ثَابِت عِمْران بْن عَبْد الْعَزِيزِ بْن عُمَر بْن عَبْد الرَّحْمَنِ بْن عوف الزُّهْرِيّ",
      "val": "10"
    },
    {
      "id": "malik_enes",
      "name_arb": "مالك بْن أنس الأصبحي ",
      "val": "10"
    },
    {
      "id": "muhriz_harun",
      "name_arb": "محرز بْن هارون القرشي ",
      "val": "10"
    },
    {
      "id": "muhamed_ibrahim",
      "name_arb": "محمد بْن إِبْرَاهِيم بْن دينار المدني الفقيه ",
      "val": "10"
    },
    {
      "id": "mugire_abdrrahman",
      "name_arb": "المغيرة بْن عَبْد الرحمن بن الحارث ابن عَبد اللَّهِ بْن عياش بْن أَبي ربيعة المخزومي ",
      "val": "10"
    },
    {
      "id": "musa_shejbe",
      "name_arb": "موسى بْن شَيْبَة بْن عَمْرو بْن عَبد اللَّهِ بْن كعب بْن مَالِك الأَنْصارِيّ",
      "val": "10"
    },
    {
      "id": "jahja_imran",
      "name_arb": "يحيى بْن عِمْران القرشي",
      "val": "10"
    },
    {
      "id": "jusuf_jakub",
      "name_arb": "يوسف بْن يَعْقُوب بْن أَبي سَلَمَة الماجشون",
      "val": "10"
    },
    {
      "id": "ahmed_ishak",
      "name_arb": "أَحْمَد بْن إسحاق الحضرمي",
      "val": "10"
    },
    {
      "id": "ezher_sad",
      "name_arb": "أزهر بْن سعد السمان",
      "val": "10"
    },
    {
      "id": "bishr_hasen",
      "name_arb": "بشر بْن الْحَسَن البَصْرِيّ",
      "val": "10"
    },
    {
      "id": "sufjan_ujejne",
      "name_arb": "سفيان بْن عُيَيْنَة ",
      "val": "10"
    },
    {
      "id": "abdvehab_abdmexhid",
      "name_arb": "عبد الوهاب بْن عَبد المجيد الثقفي ",
      "val": "10"
    },
    {
      "id": "omer_ali",
      "name_arb": "عُمَر بْن علي بْن عَطَاء بْن مقدم المقدمي",
      "val": "10"
    },
    {
      "id": "umejr_abdmexhid",
      "name_arb": "عمير بْن عَبد المجيد الحنفي",
      "val": "10"
    },
    {
      "id": "muhamed_xhafer",
      "name_arb": "محمد بْن جَعْفَر غندر",
      "val": "10"
    },
    {
      "id": "muhamed_halid",
      "name_arb": "محمد بن خالد ابن عثمة",
      "val": "10"
    },
    {
      "id": "muhamed_eadij",
      "name_arb": "محمد بْن أَبي عَدِيّ",
      "val": "10"
    },
    {
      "id": "muadh_hisham",
      "name_arb": "معاذ بْن هشام الدستوائي",
      "val": "10"
    },
    {
      "id": "mugire_seleme",
      "name_arb": "المغيرة بْن سَلَمَة أبِي هشام المخزومي",
      "val": "10"
    },
    {
      "id": "nadr_kethir",
      "name_arb": "النضر بْن كثير السعدي",
      "val": "10"
    },
    {
      "id": "jakub_ishak",
      "name_arb": "يعقوب بْن إسحاق الحضرمي",
      "val": "10"
    },
    {
      "id": "nadr_muhamed",
      "name_arb": "النضر بن محمد الجرشي",
      "val": "10"
    },
    {
      "id": "halid_jezid",
      "name_arb": "خالد بْن يزيد بْن أسد بْن عَبد اللَّهِ القسري",
      "val": "10"
    },
    {
      "id": "abdullah_abdrrahman",
      "name_arb": "عبد الله بْن عَبْد الرَّحْمَنِ",
      "val": "10"
    },
    {
      "id": "isa_junus",
      "name_arb": "عيسى بْن يونس بْن أَبي إسحاق السبيعي",
      "val": "10"
    },
    {
      "id": "ibrahim_sulejman_hanefi",
      "name_arb": "إِبْرَاهِيم بْن سُلَيْمان الحنفي",
      "val": "10"
    },
    {
      "id": "bekr_muhamed",
      "name_arb": "بكر بْن محمد العابد",
      "val": "10"
    },
    {
      "id": "habab",
      "name_arb": "حباب",
      "val": "10"
    },
    {
      "id": "ehurejra_muktib",
      "name_arb": "أَبِي هُرَيْرة المكتب",
      "val": "10"
    },
    {
      "id": "ubejdullah_ubejdrrahman",
      "name_arb": "عُبَيد الله بْن عُبَيد الرحمن الأشجعي ",
      "val": "10"
    },
    {
      "id": "othman_muzahim",
      "name_arb": "عثمان بْن مزاحم",
      "val": "10"
    },
    {
      "id": "emuavije_darir",
      "name_arb": "أبِي معاوية الضرير",
      "val": "10"
    },
    {
      "id": "muhamed_abdvehab",
      "name_arb": "محمد بن عبد الوهاب القناد"
    },
    {
      "id": "muhamed_fadl_muhelhel]",
      "name_arb": "محمد بْن الفضل بْن مهلهل",
      "val": "10"
    },
    {
      "id": "musafir_kureshi",
      "name_arb": "مسافر القرشي",
      "val": "10"
    },
    {
      "id": "neufel_mutahir",
      "name_arb": "نوفل بْن مطهر الضبي",
      "val": "10"
    },
    {
      "id": "hatim_ismail",
      "name_arb": "حاتم بْن إِسْمَاعِيل المدني ",
      "val": "10"
    },
    {
      "id": "abdrrahman_sad",
      "name_arb": "عبد الرحمن بْن سعد بن عمار الموذن",
      "val": "10"
    },
    {
      "id": "fadl_musa",
      "name_arb": "الفضل بْن مُوسَى السيناني ",
      "val": "10"
    }
  ],
  "links": [
    {
      "source": "ibrahim_sad_zuhri",
      "target": "ahmed_ibrahim_halid"
    },
    {
      "source": "ibrahim_sulejman",
      "target": "ahmed_ibrahim_halid"
    },
    {
      "source": "ismail_ibrahim_uleje",
      "target": "ahmed_ibrahim_halid"
    },
    {
      "source": "xhafer_sulejman",
      "target": "ahmed_ibrahim_halid"
    },
    {
      "source": "habib_habib_kufi",
      "target": "ahmed_ibrahim_halid"
    },
    {
      "source": "hakem_sinan",
      "target": "ahmed_ibrahim_halid"
    },
    {
      "source": "hakem_dhahir",
      "target": "ahmed_ibrahim_halid"
    },
    {
      "source": "hamad_zejd",
      "target": "ahmed_ibrahim_halid"
    },
    {
      "source": "halef_halife",
      "target": "ahmed_ibrahim_halid"
    },
    {
      "source": "seid_abdrrahman",
      "target": "ahmed_ibrahim_halid"
    },
    {
      "source": "selam_selim",
      "target": "ahmed_ibrahim_halid"
    },
    {
      "source": "selam_sulejman",
      "target": "ahmed_ibrahim_halid"
    },
    {
      "source": "sejf_harun",
      "target": "ahmed_ibrahim_halid"
    },
    {
      "source": "sherik_abdullah",
      "target": "ahmed_ibrahim_halid"
    },
    {
      "source": "salih_omer",
      "target": "ahmed_ibrahim_halid"
    },
    {
      "source": "subej_eshath",
      "target": "ahmed_ibrahim_halid"
    },
    {
      "source": "abther_kasim",
      "target": "ahmed_ibrahim_halid"
    },
    {
      "source": "abdullah_xhafer_medini",
      "target": "ahmed_ibrahim_halid"
    },
    {
      "source": "abdullah_mubarek",
      "target": "ahmed_ibrahim_halid"
    },
    {
      "source": "omer_ubejd",
      "target": "ahmed_ibrahim_halid"
    },
    {
      "source": "ferexh_fedale",
      "target": "ahmed_ibrahim_halid"
    },
    {
      "source": "muhamed_thabit",
      "target": "ahmed_ibrahim_halid"
    },
    {
      "source": "muavije_abdkerim",
      "target": "ahmed_ibrahim_halid"
    },
    {
      "source": "nasih_ala",
      "target": "ahmed_ibrahim_halid"
    },
    {
      "source": "nuh_kajs",
      "target": "ahmed_ibrahim_halid"
    },
    {
      "source": "vedah_abdullah",
      "target": "ahmed_ibrahim_halid"
    },
    {
      "source": "jezid_zurej",
      "target": "ahmed_ibrahim_halid"
    },
    {
      "source": "jusuf_atije",
      "target": "ahmed_ibrahim_halid"
    },
    {
      "source": "ibrahim_mehdi",
      "target": "ahmed_ibrahim_esdi"
    },
    {
      "source": "ahmed_ebekr",
      "target": "ahmed_ibrahim_esdi"
    },
    {
      "source": "ahmed_eshuajb",
      "target": "ahmed_ibrahim_esdi"
    },
    {
      "source": "ahmed_abdullah_junus",
      "target": "ahmed_ibrahim_esdi"
    },
    {
      "source": "ahmed_muhamed_thabit",
      "target": "ahmed_ibrahim_esdi"
    },
    {
      "source": "ishak_ibrahim_jezid",
      "target": "ahmed_ibrahim_esdi"
    },
    {
      "source": "ishak_seid_arkon",
      "target": "ahmed_ibrahim_esdi"
    },
    {
      "source": "ismail_ibrahim_mamer",
      "target": "ahmed_ibrahim_esdi"
    },
    {
      "source": "ismail_ubejd",
      "target": "ahmed_ibrahim_esdi"
    },
    {
      "source": "hamad_jahja",
      "target": "ahmed_ibrahim_esdi"
    },
    {
      "source": "hasen_isa",
      "target": "ahmed_ibrahim_esdi"
    },
    {
      "source": "rebii_nafii",
      "target": "ahmed_ibrahim_esdi"
    },
    {
      "source": "seid_hafs",
      "target": "ahmed_ibrahim_esdi"
    },
    {
      "source": "sulejman_abdrrahman",
      "target": "ahmed_ibrahim_esdi"
    },
    {
      "source": "amir_ismail",
      "target": "ahmed_ibrahim_esdi"
    },
    {
      "source": "abad_musa",
      "target": "ahmed_ibrahim_esdi"
    },
    {
      "source": "abdullah_ahmed_mukri",
      "target": "ahmed_ibrahim_esdi"
    },
    {
      "source": "abdullah_rebia",
      "target": "ahmed_ibrahim_esdi"
    },
    {
      "source": "abdullah_muhamed_kermani",
      "target": "ahmed_ibrahim_esdi"
    },
    {
      "source": "abdullah_muhamed_harrani",
      "target": "ahmed_ibrahim_esdi"
    },
    {
      "source": "abdrrahman_ibrahim_dimeshk",
      "target": "ahmed_ibrahim_esdi"
    },
    {
      "source": "abdmelik_seid",
      "target": "ahmed_ibrahim_esdi"
    },
    {
      "source": "abdvehab_nexhde",
      "target": "ahmed_ibrahim_esdi"
    },
    {
      "source": "omer_jezid",
      "target": "ahmed_ibrahim_esdi"
    },
    {
      "source": "isa_sulejman",
      "target": "ahmed_ibrahim_esdi"
    },
    {
      "source": "mahbub_musa",
      "target": "ahmed_ibrahim_esdi"
    },
    {
      "source": "muhamed_adem_mesisi",
      "target": "ahmed_ibrahim_esdi"
    },
    {
      "source": "muhamed_ismail_basri",
      "target": "ahmed_ibrahim_esdi"
    },
    {
      "source": "muhamed_selam_entaki",
      "target": "ahmed_ibrahim_esdi"
    },
    {
      "source": "muhamed_kasim_harrani",
      "target": "ahmed_ibrahim_esdi"
    },
    {
      "source": "muhamed_kudame_mesisi",
      "target": "ahmed_ibrahim_esdi"
    },
    {
      "source": "muhamed_musafa_mesisi",
      "target": "ahmed_ibrahim_esdi"
    },
    {
      "source": "mahmud_halid",
      "target": "ahmed_ibrahim_esdi"
    },
    {
      "source": "musejeb_vadih",
      "target": "ahmed_ibrahim_esdi"
    },
    {
      "source": "muafa_sulejman",
      "target": "ahmed_ibrahim_esdi"
    },
    {
      "source": "musa_ejub_nasibi",
      "target": "ahmed_ibrahim_esdi"
    },
    {
      "source": "hisham_amar",
      "target": "ahmed_ibrahim_esdi"
    },
    {
      "source": "vehb_bejan",
      "target": "ahmed_ibrahim_esdi"
    },
    {
      "source": "ahmed_abdullah_junus",
      "target": "ahmed_ibrahim_kethir"
    },
    {
      "source": "ahmed_nasr_malik",
      "target": "ahmed_ibrahim_kethir"
    },
    {
      "source": "ishak_jusuf",
      "target": "ahmed_ibrahim_kethir"
    },
    {
      "source": "ismail_ibrahim_uleje",
      "target": "ahmed_ibrahim_kethir"
    },
    {
      "source": "bekr_abdrrahman",
      "target": "ahmed_ibrahim_kethir"
    },
    {
      "source": "bukejr_muhamed",
      "target": "ahmed_ibrahim_kethir"
    },
    {
      "source": "behz_esed",
      "target": "ahmed_ibrahim_kethir"
    },
    {
      "source": "xherir_abdhamid",
      "target": "ahmed_ibrahim_kethir"
    },
    {
      "source": "haxhaxh_muhamed",
      "target": "ahmed_ibrahim_kethir"
    },
    {
      "source": "hafs_gijath",
      "target": "ahmed_ibrahim_kethir"
    },
    {
      "source": "hamad_usame",
      "target": "ahmed_ibrahim_kethir"
    },
    {
      "source": "halid_mahled",
      "target": "ahmed_ibrahim_kethir"
    },
    {
      "source": "ribij_ibrahim",
      "target": "ahmed_ibrahim_kethir"
    },
    {
      "source": "rejhan_seid",
      "target": "ahmed_ibrahim_kethir"
    },
    {
      "source": "zuhejr_neim",
      "target": "ahmed_ibrahim_kethir"
    },
    {
      "source": "shebabe_sevar",
      "target": "ahmed_ibrahim_kethir"
    },
    {
      "source": "shuxha_velid",
      "target": "ahmed_ibrahim_kethir"
    },
    {
      "source": "safvan_isa",
      "target": "ahmed_ibrahim_kethir"
    },
    {
      "source": "talk_ganam",
      "target": "ahmed_ibrahim_kethir"
    },
    {
      "source": "abdullah_xhafer_reki",
      "target": "ahmed_ibrahim_kethir"
    },
    {
      "source": "abdullah_salih_ixhli",
      "target": "ahmed_ibrahim_kethir"
    },
    {
      "source": "abdullah_mesleme_kanebi",
      "target": "ahmed_ibrahim_kethir"
    },
    {
      "source": "abdrrahman_mehdi",
      "target": "ahmed_ibrahim_kethir"
    },
    {
      "source": "abdrrahim_abdrrahman",
      "target": "ahmed_ibrahim_kethir"
    },
    {
      "source": "abdselam_abdrrahman",
      "target": "ahmed_ibrahim_kethir"
    },
    {
      "source": "abdsamed_abdvarith",
      "target": "ahmed_ibrahim_kethir"
    },
    {
      "source": "abdkebir_abdmexhid",
      "target": "ahmed_ibrahim_kethir"
    },
    {
      "source": "abdmelik_amr",
      "target": "ahmed_ibrahim_kethir"
    },
    {
      "source": "ubejdullah_musa",
      "target": "ahmed_ibrahim_kethir"
    },
    {
      "source": "omer_hafs_gijath",
      "target": "ahmed_ibrahim_kethir"
    },
    {
      "source": "ala_abdxhebar",
      "target": "ahmed_ibrahim_kethir"
    },
    {
      "source": "kutejbe_seid",
      "target": "ahmed_ibrahim_kethir"
    },
    {
      "source": "mubeshir_ismail",
      "target": "ahmed_ibrahim_kethir"
    },
    {
      "source": "muhamed_omer",
      "target": "ahmed_ibrahim_kethir"
    },
    {
      "source": "muhamed_kethir_mesisi",
      "target": "ahmed_ibrahim_kethir"
    },
    {
      "source": "muhamed_mukatil",
      "target": "ahmed_ibrahim_kethir"
    },
    {
      "source": "muhamed_jezid_meki",
      "target": "ahmed_ibrahim_kethir"
    },
    {
      "source": "musa_ismail",
      "target": "ahmed_ibrahim_kethir"
    },
    {
      "source": "hushejm_beshir",
      "target": "ahmed_ibrahim_kethir"
    },
    {
      "source": "vekii_xherrah",
      "target": "ahmed_ibrahim_kethir"
    },
    {
      "source": "vehb_bekije",
      "target": "ahmed_ibrahim_kethir"
    },
    {
      "source": "vehb_xherir",
      "target": "ahmed_ibrahim_kethir"
    },
    {
      "source": "jezid_zurej",
      "target": "ahmed_ibrahim_kethir"
    },
    {
      "source": "jezid_harun",
      "target": "ahmed_ibrahim_kethir"
    },
    {
      "source": "ibrahim_seid",
      "target": "ahmed_ibrahim_ertah"
    },
    {
      "source": "ibrahim_abdullah_ala",
      "target": "ahmed_ibrahim_ertah"
    },
    {
      "source": "ibrahim_muhamed_kureshi",
      "target": "ahmed_ibrahim_ertah"
    },
    {
      "source": "ibrahim_muhamed_jusuf",
      "target": "ahmed_ibrahim_ertah"
    },
    {
      "source": "ibrahim_mundhir",
      "target": "ahmed_ibrahim_ertah"
    },
    {
      "source": "musab_ahmed",
      "target": "ahmed_ibrahim_ertah"
    },
    {
      "source": "ahmed_ehavari",
      "target": "ahmed_ibrahim_ertah"
    },
    {
      "source": "ahmed_amr",
      "target": "ahmed_ibrahim_ertah"
    },
    {
      "source": "ishak_ibrahim_jezid",
      "target": "ahmed_ibrahim_ertah"
    },
    {
      "source": "ishak_seid_arkon",
      "target": "ahmed_ibrahim_ertah"
    },
    {
      "source": "ejub_muktib",
      "target": "ahmed_ibrahim_ertah"
    },
    {
      "source": "hamad_malik",
      "target": "ahmed_ibrahim_ertah"
    },
    {
      "source": "halid_amr",
      "target": "ahmed_ibrahim_ertah"
    },
    {
      "source": "zuhejr_abad",
      "target": "ahmed_ibrahim_ertah"
    },
    {
      "source": "seid_abdxhebar",
      "target": "ahmed_ibrahim_ertah"
    },
    {
      "source": "sulejman_seleme",
      "target": "ahmed_ibrahim_ertah"
    },
    {
      "source": "sulejman_abdrrahman",
      "target": "ahmed_ibrahim_ertah"
    },
    {
      "source": "abas_abdrrahman",
      "target": "ahmed_ibrahim_ertah"
    },
    {
      "source": "abdhamid_bekar",
      "target": "ahmed_ibrahim_ertah"
    },
    {
      "source": "abdrrahman_jahja_mahzum",
      "target": "ahmed_ibrahim_ertah"
    },
    {
      "source": "abdmelik_shuajb",
      "target": "ahmed_ibrahim_ertah"
    },
    {
      "source": "omer_hafs_bezaz",
      "target": "ahmed_ibrahim_ertah"
    },
    {
      "source": "omer_othman_himsi",
      "target": "ahmed_ibrahim_ertah"
    },
    {
      "source": "kethir_jezid",
      "target": "ahmed_ibrahim_ertah"
    },
    {
      "source": "muhamed_adem_mesisi",
      "target": "ahmed_ibrahim_ertah"
    },
    {
      "source": "muhamed_aidh",
      "target": "ahmed_ibrahim_ertah"
    },
    {
      "source": "muhamed_abdullah_bekar",
      "target": "ahmed_ibrahim_ertah"
    },
    {
      "source": "muhamed_othman",
      "target": "ahmed_ibrahim_ertah"
    },
    {
      "source": "muhamed_musafa_mesisi",
      "target": "ahmed_ibrahim_ertah"
    },
    {
      "source": "muhamed_jezid_tarsusi",
      "target": "ahmed_ibrahim_ertah"
    },
    {
      "source": "musejeb_vadih",
      "target": "ahmed_ibrahim_ertah"
    },
    {
      "source": "mehdi_xhafer",
      "target": "ahmed_ibrahim_ertah"
    },
    {
      "source": "musa_ejub_nasibi",
      "target": "ahmed_ibrahim_ertah"
    },
    {
      "source": "nasr_muhamed",
      "target": "ahmed_ibrahim_ertah"
    },
    {
      "source": "hudje_abdvehab",
      "target": "ahmed_ibrahim_ertah"
    },
    {
      "source": "jezid_halid",
      "target": "ahmed_ibrahim_ertah"
    },
    {
      "source": "jakub_humejd_medeni",
      "target": "ahmed_ibrahim_ertah"
    },
    {
      "source": "ibrahim_hakem_eban",
      "target": "ahmed_ezher"
    },
    {
      "source": "adem_eijas",
      "target": "ahmed_ezher"
    },
    {
      "source": "esbat_muhamed",
      "target": "ahmed_ezher"
    },
    {
      "source": "ishak_sulejman",
      "target": "ahmed_ezher"
    },
    {
      "source": "ishak_mensur",
      "target": "ahmed_ezher"
    },
    {
      "source": "ismail_abdkerim",
      "target": "ahmed_ezher"
    },
    {
      "source": "ismail_omer",
      "target": "ahmed_ezher"
    },
    {
      "source": "enes_ijad",
      "target": "ahmed_ezher"
    },
    {
      "source": "xharud_jezid",
      "target": "ahmed_ezher"
    },
    {
      "source": "hamad_usame",
      "target": "ahmed_ezher"
    },
    {
      "source": "reuh_ubade",
      "target": "ahmed_ezher"
    },
    {
      "source": "zejd_habab",
      "target": "ahmed_ezher"
    },
    {
      "source": "zejd_jahja",
      "target": "ahmed_ezher"
    },
    {
      "source": "seid_amir",
      "target": "ahmed_ezher"
    },
    {
      "source": "sulejman_harb",
      "target": "ahmed_ezher"
    },
    {
      "source": "suvejd_seid",
      "target": "ahmed_ezher"
    },
    {
      "source": "dahak_mahled",
      "target": "ahmed_ezher"
    },
    {
      "source": "abdullah_xhafer_reki",
      "target": "ahmed_ezher"
    },
    {
      "source": "abdullah_zubejr_humejd",
      "target": "ahmed_ezher"
    },
    {
      "source": "abdullah_salih_misri",
      "target": "ahmed_ezher"
    },
    {
      "source": "abdullah_mejmun",
      "target": "ahmed_ezher"
    },
    {
      "source": "abdullah_numejr",
      "target": "ahmed_ezher"
    },
    {
      "source": "abdrrahman_vakid",
      "target": "ahmed_ezher"
    },
    {
      "source": "abdrrezak_hemam",
      "target": "ahmed_ezher"
    },
    {
      "source": "abdaziz_hatab",
      "target": "ahmed_ezher"
    },
    {
      "source": "abdmelik_ibrahim",
      "target": "ahmed_ezher"
    },
    {
      "source": "abdmelik_amr",
      "target": "ahmed_ezher"
    },
    {
      "source": "ali_asim",
      "target": "ahmed_ezher"
    },
    {
      "source": "omer_othman_reki",
      "target": "ahmed_ezher"
    },
    {
      "source": "kurejsh_enes",
      "target": "ahmed_ezher"
    },
    {
      "source": "malik_seir",
      "target": "ahmed_ezher"
    },
    {
      "source": "muhamed_ismail_efudejk",
      "target": "ahmed_ezher"
    },
    {
      "source": "muhamed_bishr_abdi",
      "target": "ahmed_ezher"
    },
    {
      "source": "muhamed_bilal",
      "target": "ahmed_ezher"
    },
    {
      "source": "muhamed_sulejman",
      "target": "ahmed_ezher"
    },
    {
      "source": "muhamed_shurahbil",
      "target": "ahmed_ezher"
    },
    {
      "source": "muhamed_abdullah_ensari",
      "target": "ahmed_ezher"
    },
    {
      "source": "muhamed_ubejd",
      "target": "ahmed_ezher"
    },
    {
      "source": "muhamed_isa_taba",
      "target": "ahmed_ezher"
    },
    {
      "source": "muhamed_fadl_sedus",
      "target": "ahmed_ezher"
    },
    {
      "source": "muhamed_kethir_mesisi",
      "target": "ahmed_ezher"
    },
    {
      "source": "muhamed_jusuf_firjabi",
      "target": "ahmed_ezher"
    },
    {
      "source": "mervan_muhamed",
      "target": "ahmed_ezher"
    },
    {
      "source": "muala_mensur",
      "target": "ahmed_ezher"
    },
    {
      "source": "hisham_abdmelik",
      "target": "ahmed_ezher"
    },
    {
      "source": "hejthem_xhemil",
      "target": "ahmed_ezher"
    },
    {
      "source": "vehb_xherir",
      "target": "ahmed_ezher"
    },
    {
      "source": "jahja_adem",
      "target": "ahmed_ezher"
    },
    {
      "source": "jezid_ehakim",
      "target": "ahmed_ezher"
    },
    {
      "source": "jakub_ibrahim_zuhri",
      "target": "ahmed_ezher"
    },
    {
      "source": "jala_ubejd_tanafisi",
      "target": "ahmed_ezher"
    },
    {
      "source": "junus_muhamed_muedib",
      "target": "ahmed_ezher"
    },
    {
      "source": "sulejman_harb",
      "target": "ahmed_ishak_buhari"
    },
    {
      "source": "ubejdullah_musa",
      "target": "ahmed_ishak_buhari"
    },
    {
      "source": "othman_omer",
      "target": "ahmed_ishak_buhari"
    },
    {
      "source": "amr_asim",
      "target": "ahmed_ishak_buhari"
    },
    {
      "source": "muhamed_abdullah_ensari",
      "target": "ahmed_ishak_buhari"
    },
    {
      "source": "jahja_hamad",
      "target": "ahmed_ishak_buhari"
    },
    {
      "source": "jala_ubejd_tanafisi",
      "target": "ahmed_ishak_buhari"
    },
    {
      "source": "hamad_seleme",
      "target": "ahmed_ishak_basri"
    },
    {
      "source": "halil_merre",
      "target": "ahmed_ishak_basri"
    },
    {
      "source": "abdullah_hasan",
      "target": "ahmed_ishak_basri"
    },
    {
      "source": "abdullah_arade",
      "target": "ahmed_ishak_basri"
    },
    {
      "source": "abdaziz_muhtar",
      "target": "ahmed_ishak_basri"
    },
    {
      "source": "abdvahid_zijad",
      "target": "ahmed_ishak_basri"
    },
    {
      "source": "ikrime_amar",
      "target": "ahmed_ishak_basri"
    },
    {
      "source": "imran_halid",
      "target": "ahmed_ishak_basri"
    },
    {
      "source": "hemam_jahja",
      "target": "ahmed_ishak_basri"
    },
    {
      "source": "vedah_abdullah",
      "target": "ahmed_ishak_basri"
    },
    {
      "source": "vuhejb_halid",
      "target": "ahmed_ishak_basri"
    },
    {
      "source": "jahja_seid",
      "target": "ahmed_ishak_basri"
    },
    {
      "source": "haxhaxh_nusajr",
      "target": "ahmed_ishak_ehvazi"
    },
    {
      "source": "halad_jahja",
      "target": "ahmed_ishak_ehvazi"
    },
    {
      "source": "rebii_nafii",
      "target": "ahmed_ishak_ehvazi"
    },
    {
      "source": "amir_mudrik",
      "target": "ahmed_ishak_ehvazi"
    },
    {
      "source": "abdullah_serij",
      "target": "ahmed_ishak_ehvazi"
    },
    {
      "source": "abdullah_jezid",
      "target": "ahmed_ishak_ehvazi"
    },
    {
      "source": "muhamed_abdullah_zubejri",
      "target": "ahmed_ishak_ehvazi"
    },
    {
      "source": "musa_davud",
      "target": "ahmed_ishak_ehvazi"
    },
    {
      "source": "jala_abad",
      "target": "ahmed_ishak_ehvazi"
    },
    {
      "source": "ibrahim_sad_zuhri",
      "target": "ahmed_ismail_medeni"
    },
    {
      "source": "hatim_ismail",
      "target": "ahmed_ismail_medeni"
    },
    {
      "source": "sad_seid",
      "target": "ahmed_ismail_medeni"
    },
    {
      "source": "abdrrahaman_ezinad",
      "target": "ahmed_ismail_medeni"
    },
    {
      "source": "abdaziz_imran",
      "target": "ahmed_ismail_medeni"
    },
    {
      "source": "abdaziz_muhamed",
      "target": "ahmed_ismail_medeni"
    },
    {
      "source": "kethir_xhafer",
      "target": "ahmed_ismail_medeni"
    },
    {
      "source": "malik_enes",
      "target": "ahmed_ismail_medeni"
    },
    {
      "source": "muhamed_ismail_efudejk",
      "target": "ahmed_ismail_medeni"
    },
    {
      "source": "muslim_halid",
      "target": "ahmed_ismail_medeni"
    },
    {
      "source": "musab_abdullah",
      "target": "ahmed_ismail_medeni"
    },
    {
      "source": "ismail_ibrahim_tejmi",
      "target": "ahmed_ismail_medeni"
    },
    {
      "source": "rifaa_ijas",
      "target": "ahmed_ishkab"
    },
    {
      "source": "sherik_abdullah",
      "target": "ahmed_ishkab"
    },
    {
      "source": "abdrrahman_abdmelik",
      "target": "ahmed_ishkab"
    },
    {
      "source": "abdrrahman_muhamed_muharibi",
      "target": "ahmed_ishkab"
    },
    {
      "source": "abdrrahim_sulejman",
      "target": "ahmed_ishkab"
    },
    {
      "source": "abdselam_harb",
      "target": "ahmed_ishkab"
    },
    {
      "source": "ali_abis",
      "target": "ahmed_ishkab"
    },
    {
      "source": "kasim_malik",
      "target": "ahmed_ishkab"
    },
    {
      "source": "muhamed_bishr_abdi",
      "target": "ahmed_ishkab"
    },
    {
      "source": "muhamed_ubejd",
      "target": "ahmed_ishkab"
    },
    {
      "source": "muhamed_fudajl",
      "target": "ahmed_ishkab"
    },
    {
      "source": "jahja_jala",
      "target": "ahmed_ishkab"
    },
    {
      "source": "ebekr_ajash",
      "target": "ahmed_ishkab"
    },
    {
      "source": "sufjan_habib",
      "target": "ahmed_ejub"
    },
    {
      "source": "sehl_eslem",
      "target": "ahmed_ejub"
    },
    {
      "source": "shebabe_sevar",
      "target": "ahmed_ejub"
    },
    {
      "source": "abdala_abdala",
      "target": "ahmed_ejub"
    },
    {
      "source": "abdvarith_seid",
      "target": "ahmed_ejub"
    },
    {
      "source": "aubid_eimran",
      "target": "ahmed_ejub"
    },
    {
      "source": "mesleme_alkame",
      "target": "ahmed_ejub"
    },
    {
      "source": "ibrahim_ujejne",
      "target": "ahmed_budejl"
    },
    {
      "source": "ishak_sulejman",
      "target": "ahmed_budejl"
    },
    {
      "source": "xhabir_nuh",
      "target": "ahmed_budejl"
    },
    {
      "source": "hafs_gijath",
      "target": "ahmed_budejl"
    },
    {
      "source": "hamad_usame",
      "target": "ahmed_budejl"
    },
    {
      "source": "abdullah_idris",
      "target": "ahmed_budejl"
    },
    {
      "source": "abdullah_mejmun",
      "target": "ahmed_budejl"
    },
    {
      "source": "abdullah_numejr",
      "target": "ahmed_budejl"
    },
    {
      "source": "abdrrahman_muhamed_muharibi",
      "target": "ahmed_budejl"
    },
    {
      "source": "utham_ali",
      "target": "ahmed_budejl"
    },
    {
      "source": "isa_rashid",
      "target": "ahmed_budejl"
    },
    {
      "source": "muhamed_hazim",
      "target": "ahmed_budejl"
    },
    {
      "source": "emuavije_darir",
      "target": "ahmed_budejl"
    },
    {
      "source": "muhamed_fudajl",
      "target": "ahmed_budejl"
    },
    {
      "source": "mufedal_salih",
      "target": "ahmed_budejl"
    },
    {
      "source": "vekii_xherrah",
      "target": "ahmed_budejl"
    },
    {
      "source": "jahja_isa",
      "target": "ahmed_budejl"
    },
    {
      "source": "ebekr_ajash",
      "target": "ahmed_budejl"
    },
    {
      "source": "ismail_ehalid",
      "target": "ahmed_beshir"
    },
    {
      "source": "hafs_emensur",
      "target": "ahmed_beshir"
    },
    {
      "source": "seid_earube",
      "target": "ahmed_beshir"
    },
    {
      "source": "sulejman_mihran",
      "target": "ahmed_beshir"
    },
    {
      "source": "shebib_bishr",
      "target": "ahmed_beshir"
    },
    {
      "source": "shube_haxhaxh",
      "target": "ahmed_beshir"
    },
    {
      "source": "abdullah_shubrume",
      "target": "ahmed_beshir"
    },
    {
      "source": "ubejdullah_omer",
      "target": "ahmed_beshir"
    },
    {
      "source": "alil_bexheli",
      "target": "ahmed_beshir"
    },
    {
      "source": "omer_hamze",
      "target": "ahmed_beshir"
    },
    {
      "source": "avane_hakem",
      "target": "ahmed_beshir"
    },
    {
      "source": "isa_mejmun",
      "target": "ahmed_beshir"
    },
    {
      "source": "muxhalid_seid",
      "target": "ahmed_beshir"
    },
    {
      "source": "muhamed_eismail",
      "target": "ahmed_beshir"
    },
    {
      "source": "misar_kidam",
      "target": "ahmed_beshir"
    },
    {
      "source": "harun_antere",
      "target": "ahmed_beshir"
    },
    {
      "source": "hisham_hashim",
      "target": "ahmed_beshir"
    },
    {
      "source": "hisham_hasan",
      "target": "ahmed_beshir"
    },
    {
      "source": "hisham_urve",
      "target": "ahmed_beshir"
    },
    {
      "source": "jahja_sulejman",
      "target": "ahmed_beshir"
    },
    {
      "source": "bishr_serij",
      "target": "ahmed_bekar"
    },
    {
      "source": "beshir_abdullah",
      "target": "ahmed_bekar"
    },
    {
      "source": "bekar_emejmune",
      "target": "ahmed_bekar"
    },
    {
      "source": "xhafer_aun",
      "target": "ahmed_bekar"
    },
    {
      "source": "abdhamid_abdrrahman",
      "target": "ahmed_bekar"
    },
    {
      "source": "muhamed_hazim",
      "target": "ahmed_bekar"
    },
    {
      "source": "emuavije_darir",
      "target": "ahmed_bekar"
    },
    {
      "source": "muhamed_seleme",
      "target": "ahmed_bekar"
    },
    {
      "source": "muhamed_fudajl",
      "target": "ahmed_bekar"
    },
    {
      "source": "mahled_jezid",
      "target": "ahmed_bekar"
    },
    {
      "source": "vekii_xherrah",
      "target": "ahmed_bekar"
    },
    {
      "source": "vehb_ismail",
      "target": "ahmed_bekar"
    },
    {
      "source": "eseid_mbhashim",
      "target": "ahmed_bekar"
    },
    {
      "source": "abdullah_vakid",
      "target": "ahmed_bekar"
    },
    {
      "source": "ibrahim_sad_zuhri",
      "target": "ahmed_ebekr"
    },
    {
      "source": "husejn_zejd",
      "target": "ahmed_ebekr"
    },
    {
      "source": "salih_kidame",
      "target": "ahmed_ebekr"
    },
    {
      "source": "asim_suvejd",
      "target": "ahmed_ebekr"
    },
    {
      "source": "abdrrahman_zejd",
      "target": "ahmed_ebekr"
    },
    {
      "source": "abdaziz_ehazim",
      "target": "ahmed_ebekr"
    },
    {
      "source": "abdaziz_imran",
      "target": "ahmed_ebekr"
    },
    {
      "source": "abdaziz_muhamed",
      "target": "ahmed_ebekr"
    },
    {
      "source": "abdmuhejmin_abas",
      "target": "ahmed_ebekr"
    },
    {
      "source": "ataf_halid",
      "target": "ahmed_ebekr"
    },
    {
      "source": "omer_talha",
      "target": "ahmed_ebekr"
    },
    {
      "source": "imran_abdaziz",
      "target": "ahmed_ebekr"
    },
    {
      "source": "malik_enes",
      "target": "ahmed_ebekr"
    },
    {
      "source": "muhriz_harun",
      "target": "ahmed_ebekr"
    },
    {
      "source": "muhamed_ibrahim",
      "target": "ahmed_ebekr"
    },
    {
      "source": "mugire_abdrrahman",
      "target": "ahmed_ebekr"
    },
    {
      "source": "musa_shejbe",
      "target": "ahmed_ebekr"
    },
    {
      "source": "jahja_imran",
      "target": "ahmed_ebekr"
    },
    {
      "source": "jusuf_jakub",
      "target": "ahmed_ebekr"
    },
    {
      "source": "ahmed_ishak",
      "target": "ahmed_thabit"
    },
    {
      "source": "ezher_sad",
      "target": "ahmed_thabit"
    },
    {
      "source": "bishr_hasen",
      "target": "ahmed_thabit"
    },
    {
      "source": "sufjan_ujejne",
      "target": "ahmed_thabit"
    },
    {
      "source": "safvan_isa",
      "target": "ahmed_thabit"
    },
    {
      "source": "abdrrahman_mehdi",
      "target": "ahmed_thabit"
    },
    {
      "source": "abdvehab_abdmexhid",
      "target": "ahmed_thabit"
    },
    {
      "source": "omer_ali",
      "target": "ahmed_thabit"
    },
    {
      "source": "umejr_abdmexhid",
      "target": "ahmed_thabit"
    },
    {
      "source": "muhamed_xhafer",
      "target": "ahmed_thabit"
    },
    {
      "source": "muhamed_halid",
      "target": "ahmed_thabit"
    },
    {
      "source": "muhamed_eadij",
      "target": "ahmed_thabit"
    },
    {
      "source": "muadh_hisham",
      "target": "ahmed_thabit"
    },
    {
      "source": "mugire_seleme",
      "target": "ahmed_thabit"
    },
    {
      "source": "nadr_kethir",
      "target": "ahmed_thabit"
    },
    {
      "source": "vekii_xherrah",
      "target": "ahmed_thabit"
    },
    {
      "source": "jahja_seid",
      "target": "ahmed_thabit"
    },
    {
      "source": "jakub_ishak",
      "target": "ahmed_thabit"
    },
    {
      "source": "ismail_abdkerim",
      "target": "ahmed_xhafer"
    },
    {
      "source": "nadr_muhamed",
      "target": "ahmed_xhafer"
    },
    {
      "source": "hakem_dhahir",
      "target": "ahmed_xhenab"
    },
    {
      "source": "halid_jezid",
      "target": "ahmed_xhenab"
    },
    {
      "source": "abdullah_abdrrahman",
      "target": "ahmed_xhenab"
    },
    {
      "source": "isa_junus",
      "target": "ahmed_xhenab"
    },
    {
      "source": "ibrahim_sulejman",
      "target": "ahmed_xhevas"
    },
    {
      "source": "bekr_muhamed",
      "target": "ahmed_xhevas"
    },
    {
      "source": "xherir_abdhamid",
      "target": "ahmed_xhevas"
    },
    {
      "source": "habab",
      "target": "ahmed_xhevas"
    },
    {
      "source": "ehurejra_muktib",
      "target": "ahmed_xhevas"
    },
    {
      "source": "sufjan_ujejne",
      "target": "ahmed_xhevas"
    },
    {
      "source": "selam_selim",
      "target": "ahmed_xhevas"
    },
    {
      "source": "abdullah_idris",
      "target": "ahmed_xhevas"
    },
    {
      "source": "abdullah_mubarek",
      "target": "ahmed_xhevas"
    },
    {
      "source": "ubejdullah_ubejdrrahman",
      "target": "ahmed_xhevas"
    },
    {
      "source": "othman_muzahim",
      "target": "ahmed_xhevas"
    },
    {
      "source": "muhamed_hazim",
      "target": "ahmed_xhevas"
    },
    {
      "source": "emuavije_darir",
      "target": "ahmed_xhevas"
    },
    {
      "source": "muhamed_abdvehab",
      "target": "ahmed_xhevas"
    },
    {
      "source": "muhamed_fadl_muhelhel",
      "target": "ahmed_xhevas"
    },
    {
      "source": "musafir_kureshi",
      "target": "ahmed_xhevas"
    },
    {
      "source": "neufel_mutahir",
      "target": "ahmed_xhevas"
    },
    {
      "source": "ebekr_ajash",
      "target": "ahmed_xhevas"
    },
    {
      "source": "enes_ijad",
      "target": "ahmed_haxhaxh"
    },
    {
      "source": "hatim_ismail",
      "target": "ahmed_haxhaxh"
    },
    {
      "source": "sufjan_ujejne",
      "target": "ahmed_haxhaxh"
    },
    {
      "source": "abdullah_mubarek",
      "target": "ahmed_haxhaxh"
    },
    {
      "source": "abdrrahman_sad",
      "target": "ahmed_haxhaxh"
    },
    {
      "source": "abdrrahman_mehdi",
      "target": "ahmed_haxhaxh"
    },
    {
      "source": "abdaziz_ehazim",
      "target": "ahmed_haxhaxh"
    },
    {
      "source": "abdaziz_muhamed",
      "target": "ahmed_haxhaxh"
    },
    {
      "source": "fadl_musa",
      "target": "ahmed_haxhaxh"
    },
    {
      "source": "musa_shejbe",
      "target": "ahmed_haxhaxh"
    }
  ]
}